IE_SAMBD2020_ADVPYTHON_GROUPE/__init__.py
IE_SAMBD2020_ADVPYTHON_GROUPE-0.1.dist-info/METADATA
IE_SAMBD2020_ADVPYTHON_GROUPE-0.1.dist-info/WHEEL
IE_SAMBD2020_ADVPYTHON_GROUPE-0.1.dist-info/top_level.txt
IE_SAMBD2020_ADVPYTHON_GROUPE-0.1.dist-info/RECORD
