Metadata-Version: 2.1
Name: IE-SAMBD2020-ADVPYTHON-GROUPE
Version: 0.1
Summary: Python Packaging Starting Kit - Simple Structure to creater your own package - for training purposes!
Home-page: https://github.com/janamia/IE_SAMBD2020_ADVPYTHON_GROUPE.git
Author: GROUPE
Author-email: jana.jindan@gmail.com
License: MIT
Platform: UNKNOWN
